mailbreeze/__init__.py
mailbreeze/client.py
mailbreeze/errors.py
mailbreeze/http_client.py
mailbreeze/resources/__init__.py
mailbreeze/resources/attachments.py
mailbreeze/resources/base.py
mailbreeze/resources/contacts.py
mailbreeze/resources/emails.py
mailbreeze/resources/lists.py
mailbreeze/resources/verification.py
mailbreeze/types/__init__.py
mailbreeze/types/attachments.py
mailbreeze/types/common.py
mailbreeze/types/contacts.py
mailbreeze/types/emails.py
mailbreeze/types/verification.py
mailbreeze-0.2.7.dist-info/METADATA
mailbreeze-0.2.7.dist-info/WHEEL
mailbreeze-0.2.7.dist-info/RECORD
