Metadata-Version: 2.4
Name: mailbreeze
Version: 0.2.7
Summary: Official Python SDK for MailBreeze email platform
Project-URL: Homepage, https://mailbreeze.com
Project-URL: Documentation, https://docs.mailbreeze.com
Project-URL: Repository, https://github.com/MailBreeze/mailbreeze-python
Project-URL: Issues, https://github.com/MailBreeze/mailbreeze-python/issues
Author-email: MailBreeze <support@mailbreeze.com>
License-Expression: MIT
Keywords: email,email-api,email-marketing,mailbreeze,sdk,transactional-email
Classifier: Development Status :: 4 - Beta
Classifier: Intended Audience :: Developers
Classifier: License :: OSI Approved :: MIT License
Classifier: Operating System :: OS Independent
Classifier: Programming Language :: Python :: 3
Classifier: Programming Language :: Python :: 3.10
Classifier: Programming Language :: Python :: 3.11
Classifier: Programming Language :: Python :: 3.12
Classifier: Programming Language :: Python :: 3.13
Classifier: Typing :: Typed
Requires-Python: >=3.10
Requires-Dist: httpx>=0.27.0
Requires-Dist: pydantic>=2.0.0
Provides-Extra: dev
Requires-Dist: mypy>=1.14.0; extra == 'dev'
Requires-Dist: pytest-asyncio>=0.24.0; extra == 'dev'
Requires-Dist: pytest-cov>=6.0.0; extra == 'dev'
Requires-Dist: pytest>=8.0.0; extra == 'dev'
Requires-Dist: respx>=0.22.0; extra == 'dev'
Requires-Dist: ruff>=0.8.0; extra == 'dev'
